freesurfer_surface/__init__.py
freesurfer_surface/__main__.py
freesurfer_surface/version.py
freesurfer_surface-2.0.0.dist-info/COPYING
freesurfer_surface-2.0.0.dist-info/METADATA
freesurfer_surface-2.0.0.dist-info/WHEEL
freesurfer_surface-2.0.0.dist-info/entry_points.txt
freesurfer_surface-2.0.0.dist-info/top_level.txt
freesurfer_surface-2.0.0.dist-info/RECORD
