Metadata-Version: 2.1
Name: freesurfer-surface
Version: 2.0.0
Summary: Python Library to Read and Write Surface Files in Freesurfer's TriangularSurface Format
Home-page: https://github.com/fphammerle/freesurfer-surface
Author: Fabian Peter Hammerle
Author-email: fabian@hammerle.me
License: GPLv3+
Keywords: brain,freesurfer,mesh,neuroimaging,reader,surface,triangle,vertex
Platform: UNKNOWN
Classifier: Development Status :: 3 - Alpha
Classifier: Intended Audience :: Healthcare Industry
Classifier: Intended Audience :: Science/Research
Classifier: Programming Language :: Python :: 3.6
Classifier: Programming Language :: Python :: 3.7
Classifier: Programming Language :: Python :: 3.8
Classifier: Programming Language :: Python :: 3.9
Classifier: Topic :: Scientific/Engineering :: Information Analysis
Classifier: Topic :: Scientific/Engineering :: Medical Science Apps.
Classifier: Topic :: Utilities
Requires-Python: >=3.6
Requires-Dist: numpy (<2)
